meesee.py
meesee-1.6.0.dist-info/LICENSE
meesee-1.6.0.dist-info/METADATA
meesee-1.6.0.dist-info/WHEEL
meesee-1.6.0.dist-info/top_level.txt
meesee-1.6.0.dist-info/RECORD
