Metadata-Version: 2.1
Name: meesee
Version: 1.6.0
Summary: Task queue, Long lived workers process parallelization, with Redis as backend
Home-page: https://github.com/Attumm/meesee
Author: Melvin Bijman
Author-email: bijman.m.m@gmail.com
License: MIT
Classifier: Development Status :: 5 - Production/Stable
Classifier: Intended Audience :: Developers
Classifier: Topic :: Database
Classifier: Topic :: System :: Distributed Computing
Classifier: License :: OSI Approved :: MIT License
Classifier: Programming Language :: Python :: 3
Classifier: Programming Language :: Python :: 3.6
Classifier: Programming Language :: Python :: 3.7
Classifier: Programming Language :: Python :: 3.8
Classifier: Programming Language :: Python :: 3.9
Classifier: Programming Language :: Python :: 3.10
Classifier: Programming Language :: Python :: 3.11
Classifier: Programming Language :: Python :: 3.12
Requires-Python: >3.5
License-File: LICENSE
Requires-Dist: redis==4.5.5
